social_connector/__init__.py
social_connector/apps.py
social_connector/views.py
django_social_connector-0.1.0.dist-info/LICENSE
django_social_connector-0.1.0.dist-info/METADATA
django_social_connector-0.1.0.dist-info/WHEEL
django_social_connector-0.1.0.dist-info/top_level.txt
django_social_connector-0.1.0.dist-info/RECORD
